rrspotipy/__init__.py
rrspotipy-0.1.0.dist-info/METADATA
rrspotipy-0.1.0.dist-info/WHEEL
rrspotipy-0.1.0.dist-info/RECORD
