Metadata-Version: 2.1
Name: rrspotipy
Version: 0.1.0
Summary: Play a playlist
License: MIT
Author: RadoTheProgrammer
Author-email: rado@arazakar.com
Requires-Python: >=3.11,<4.0
Classifier: License :: OSI Approved :: MIT License
Classifier: Programming Language :: Python :: 3
Classifier: Programming Language :: Python :: 3.11
Classifier: Programming Language :: Python :: 3.12
Requires-Dist: audioread (>=3.0.1,<4.0.0)
Requires-Dist: pygame (>=2.5.2,<3.0.0)
